Metadata-Version: 2.1
Name: dbwidgets
Version: 0.0.1
Summary: Database aware widgets for PySide2
Home-page: https://github.com/ilkermanap/dbwidgets
Author: Ilker Manap
Author-email: ilkermanap@gmail.com
License: UNKNOWN
Platform: UNKNOWN
Classifier: Programming Language :: Python :: 3
Classifier: License :: OSI Approved :: GNU Lesser General Public License v3 (LGPLv3)
Classifier: Operating System :: OS Independent
